src/__init__.py
src/main.py
src/js/agent.js
src/js/class_info.js
src/js/hook.js
src/js/modules.js
src/js/ui.js
frida_play-0.0.4.dist-info/LICENSE
frida_play-0.0.4.dist-info/METADATA
frida_play-0.0.4.dist-info/WHEEL
frida_play-0.0.4.dist-info/entry_points.txt
frida_play-0.0.4.dist-info/top_level.txt
frida_play-0.0.4.dist-info/zip-safe
frida_play-0.0.4.dist-info/RECORD
