Metadata-Version: 2.1
Name: frida-play
Version: 0.0.4
Summary: 没有描述哈
Author: Not Tom Cruise
Author-email: tangxiaoojun@gmail.com
License: MIT
Keywords: frida,ios,tom
Classifier: Natural Language :: Chinese (Simplified)
License-File: LICENSE
Requires-Dist: frida (>=16.0.11)
